flake8_import_order_grok/__init__.py
flake8_import_order_grok/import_order.py
flake8_import_order_grok-0.3.3.dist-info/LICENSE
flake8_import_order_grok-0.3.3.dist-info/METADATA
flake8_import_order_grok-0.3.3.dist-info/WHEEL
flake8_import_order_grok-0.3.3.dist-info/entry_points.txt
flake8_import_order_grok-0.3.3.dist-info/top_level.txt
flake8_import_order_grok-0.3.3.dist-info/RECORD
